[
  {
    "sofifa_id": "218717",
    "player_url": "https://sofifa.com/player/218717/gabadhino-mhango/20/159586",
    "short_name": "G. Mhango",
    "long_name": "Gabadhino Mhango",
    "age": "26",
    "dob": "27/09/1992",
    "height_cm": "178",
    "weight_kg": "73",
    "nationality": "Malawi",
    "club": "Orlando Pirates",
    "overall": "62",
    "potential": "64",
    "value_eur": "375000",
    "wage_eur": "1000",
    "player_positions": "ST",
    "preferred_foot": "Right",
    "international_reputation": "1",
    "weak_foot": "4",
    "skill_moves": "2",
    "work_rate": "High/Medium",
    "body_type": "Lean",
    "real_face": "No",
    "release_clause_eur": "834000",
    "player_tags": "",
    "team_position": "RES",
    "team_jersey_number": "7",
    "loaned_from": "",
    "joined": "01/07/2019",
    "contract_valid_until": "2022",
    "nation_position": "",
    "nation_jersey_number": "",
    "pace": "75",
    "shooting": "60",
    "passing": "43",
    "dribbling": "67",
    "defending": "21",
    "physic": "46",
    "gk_diving": "",
    "gk_handling": "",
    "gk_kicking": "",
    "gk_reflexes": "",
    "gk_speed": "",
    "gk_positioning": "",
    "player_traits": "Crowd Favourite",
    "attacking_crossing": "42",
    "attacking_finishing": "65",
    "attacking_heading_accuracy": "54",
    "attacking_short_passing": "44",
    "attacking_volleys": "33",
    "skill_dribbling": "67",
    "skill_curve": "30",
    "skill_fk_accuracy": "27",
    "skill_long_passing": "38",
    "skill_ball_control": "66",
    "movement_acceleration": "77",
    "movement_sprint_speed": "74",
    "movement_agility": "74",
    "movement_reactions": "54",
    "movement_balance": "71",
    "power_shot_power": "69",
    "power_jumping": "66",
    "power_stamina": "63",
    "power_strength": "46",
    "power_long_shots": "46",
    "mentality_aggression": "22",
    "mentality_interceptions": "18",
    "mentality_positioning": "60",
    "mentality_vision": "51",
    "mentality_penalties": "62",
    "mentality_composure": "52",
    "defending_marking": "21",
    "defending_standing_tackle": "14",
    "defending_sliding_tackle": "11",
    "goalkeeping_diving": "7",
    "goalkeeping_handling": "11",
    "goalkeeping_kicking": "12",
    "goalkeeping_positioning": "8",
    "goalkeeping_reflexes": "15",
    "ls": "60+2",
    "st": "60+2",
    "rs": "60+2",
    "lw": "60+2",
    "lf": "61+2",
    "cf": "61+2",
    "rf": "61+2",
    "rw": "60+2",
    "lam": "57+2",
    "cam": "57+2",
    "ram": "57+2",
    "lm": "58+2",
    "lcm": "49+2",
    "cm": "49+2",
    "rcm": "49+2",
    "rm": "58+2",
    "lwb": "41+2",
    "ldm": "35+2",
    "cdm": "35+2",
    "rdm": "35+2",
    "rwb": "41+2",
    "lb": "38+2",
    "lcb": "31+2",
    "cb": "31+2",
    "rcb": "31+2",
    "rb": "38+2"
  }
]